Metadata-Version: 2.1
Name: pyxtal-ff
Version: 0.2.2
Summary: Python code for force field training of crystals
Home-page: https://github.com/qzhu2017/PyXtal-FF
Author: Qiang Zhu, Howard Yanxon, David Zagaceta, Binh Tang
Author-email: qiang.zhu@unlv.edu
License: MIT
Classifier: Programming Language :: Python :: 3
Classifier: License :: OSI Approved :: MIT License
Classifier: Operating System :: OS Independent
Requires-Python: >=3.7
Requires-Dist: numpy (>=1.13.3)
Requires-Dist: scipy (>=1.6.1)
Requires-Dist: matplotlib (>=2.0.0)
Requires-Dist: ase (>=3.22.1)
Requires-Dist: torch (>=1.10.2)
Requires-Dist: phonopy (==2.3.2)
Requires-Dist: spglib (>=1.12.1)
Requires-Dist: monty (>=3.0.2)
Requires-Dist: seekpath (>=1.9.5)
Requires-Dist: numba (>=0.50.1)
